{"01":{"stateAbbr":"AL","pluralityParty":"STY","totalSeats":13,"seats":{"STY":3,"CTR":2,"DSA":1,"SD":3,"REF":2,"CON":2}},"02":{"stateAbbr":"AK","pluralityParty":"SD","totalSeats":2,"seats":{"SD":1,"STY":1}},"04":{"stateAbbr":"AZ","pluralityParty":"CON","totalSeats":19,"seats":{"CON":3,"STY":3,"SD":3,"LIB":3,"REF":3,"NAT":2,"PRG":1,"CTR":1}},"05":{"stateAbbr":"AR","pluralityParty":"CON","totalSeats":8,"seats":{"CON":2,"REF":1,"CTR":2,"STY":1,"SD":2}},"06":{"stateAbbr":"CA","pluralityParty":"STY","totalSeats":104,"seats":{"STY":20,"SD":20,"LIB":17,"CTR":15,"CON":16,"REF":13,"PRG":1,"NAT":1,"DSA":1}},"08":{"stateAbbr":"CO","pluralityParty":"SD","totalSeats":15,"seats":{"SD":3,"REF":3,"STY":3,"CON":3,"LIB":3}},"09":{"stateAbbr":"CT","pluralityParty":"SD","totalSeats":9,"seats":{"STY":2,"SD":3,"LIB":1,"CON":2,"REF":1}},"10":{"stateAbbr":"DE","pluralityParty":"SD","totalSeats":3,"seats":{"SD":1,"CON":1,"STY":1}},"11":{"stateAbbr":"DC","pluralityParty":"SD","totalSeats":2,"seats":{"SD":1,"LIB":1}},"12":{"stateAbbr":"FL","pluralityParty":"STY","totalSeats":57,"seats":{"CON":10,"STY":11,"DSA":1,"SD":11,"REF":10,"CTR":10,"LIB":3,"PRG":1}},"13":{"stateAbbr":"GA","pluralityParty":"STY","totalSeats":28,"seats":{"STY":4,"SD":4,"CON":4,"CTR":4,"REF":4,"LIB":4,"DSA":2,"NAT":2}},"15":{"stateAbbr":"HI","pluralityParty":"SD","totalSeats":4,"seats":{"SD":1,"LIB":1,"CON":1,"STY":1}},"16":{"stateAbbr":"ID","pluralityParty":"CON","totalSeats":5,"seats":{"CON":1,"REF":1,"SD":1,"CTR":1,"STY":1}},"17":{"stateAbbr":"IL","pluralityParty":"SD","totalSeats":34,"seats":{"SD":6,"CTR":3,"CON":6,"REF":5,"STY":6,"LIB":6,"DSA":1,"PRG":1}},"18":{"stateAbbr":"IN","pluralityParty":"CON","totalSeats":18,"seats":{"REF":3,"CON":4,"CTR":2,"STY":4,"SD":4,"LIB":1}},"19":{"stateAbbr":"IA","pluralityParty":"STY","totalSeats":8,"seats":{"STY":2,"CON":2,"CTR":1,"SD":2,"LIB":1}},"20":{"stateAbbr":"KS","pluralityParty":"CON","totalSeats":8,"seats":{"CON":2,"STY":2,"REF":1,"SD":1,"CTR":1,"LIB":1}},"21":{"stateAbbr":"KY","pluralityParty":"STY","totalSeats":12,"seats":{"STY":2,"SD":2,"CON":2,"CTR":1,"REF":2,"NAT":2,"LIB":1}},"22":{"stateAbbr":"LA","pluralityParty":"STY","totalSeats":12,"seats":{"STY":2,"SD":2,"REF":2,"CTR":2,"CON":2,"LIB":1,"NAT":1}},"23":{"stateAbbr":"ME","pluralityParty":"LIB","totalSeats":4,"seats":{"LIB":1,"CON":1,"REF":1,"SD":1}},"24":{"stateAbbr":"MD","pluralityParty":"SD","totalSeats":16,"seats":{"SD":4,"STY":4,"LIB":2,"CTR":1,"CON":3,"REF":1,"PRG":1}},"25":{"stateAbbr":"MA","pluralityParty":"SD","totalSeats":18,"seats":{"SD":4,"CON":3,"DSA":2,"LIB":4,"STY":3,"REF":2}},"26":{"stateAbbr":"MI","pluralityParty":"CON","totalSeats":27,"seats":{"CON":5,"DSA":1,"SD":5,"CTR":3,"STY":3,"REF":5,"LIB":4,"NAT":1}},"27":{"stateAbbr":"MN","pluralityParty":"LIB","totalSeats":15,"seats":{"SD":2,"LIB":3,"PRG":1,"CTR":2,"CON":3,"REF":2,"STY":2}},"28":{"stateAbbr":"MS","pluralityParty":"STY","totalSeats":8,"seats":{"STY":2,"SD":1,"CON":2,"REF":2,"CTR":1}},"29":{"stateAbbr":"MO","pluralityParty":"STY","totalSeats":16,"seats":{"STY":3,"SD":3,"REF":2,"CTR":2,"DSA":1,"NAT":1,"LIB":1,"CON":3}},"30":{"stateAbbr":"MT","pluralityParty":"SD","totalSeats":3,"seats":{"SD":1,"STY":1,"CON":1}},"31":{"stateAbbr":"NE","pluralityParty":"CON","totalSeats":5,"seats":{"CON":1,"SD":1,"CTR":1,"STY":1,"REF":1}},"32":{"stateAbbr":"NV","pluralityParty":"SD","totalSeats":8,"seats":{"SD":2,"STY":1,"CON":2,"REF":2,"LIB":1}},"33":{"stateAbbr":"NH","pluralityParty":"CON","totalSeats":4,"seats":{"CON":1,"SD":1,"DSA":1,"CTR":1}},"34":{"stateAbbr":"NJ","pluralityParty":"CON","totalSeats":24,"seats":{"CON":4,"REF":3,"STY":4,"SD":4,"CTR":3,"NAT":1,"LIB":4,"DSA":1}},"35":{"stateAbbr":"NM","pluralityParty":"SD","totalSeats":6,"seats":{"SD":2,"CON":2,"STY":2}},"36":{"stateAbbr":"NY","pluralityParty":"SD","totalSeats":53,"seats":{"SD":9,"STY":9,"CON":9,"REF":8,"DSA":4,"CTR":6,"LIB":8}},"37":{"stateAbbr":"NC","pluralityParty":"CON","totalSeats":27,"seats":{"CON":5,"SD":5,"STY":5,"LIB":3,"CTR":3,"DSA":1,"NAT":1,"REF":4}},"38":{"stateAbbr":"ND","pluralityParty":"REF","totalSeats":2,"seats":{"REF":1,"SD":1}},"39":{"stateAbbr":"OH","pluralityParty":"CTR","totalSeats":31,"seats":{"STY":4,"CTR":5,"REF":5,"CON":5,"SD":5,"LIB":3,"NAT":2,"DSA":2}},"40":{"stateAbbr":"OK","pluralityParty":"CON","totalSeats":10,"seats":{"CON":2,"STY":2,"REF":1,"SD":2,"CTR":2,"NAT":1}},"41":{"stateAbbr":"OR","pluralityParty":"LIB","totalSeats":11,"seats":{"CON":2,"SD":2,"STY":2,"LIB":3,"NAT":1,"REF":1}},"42":{"stateAbbr":"PA","pluralityParty":"SD","totalSeats":34,"seats":{"SD":6,"STY":5,"LIB":4,"REF":5,"PRG":2,"DSA":2,"CTR":4,"CON":5,"NAT":1}},"44":{"stateAbbr":"RI","pluralityParty":"CON","totalSeats":3,"seats":{"CON":1,"SD":1,"STY":1}},"45":{"stateAbbr":"SC","pluralityParty":"STY","totalSeats":13,"seats":{"STY":3,"REF":3,"SD":2,"CON":3,"DSA":1,"CTR":1}},"46":{"stateAbbr":"SD","pluralityParty":"CON","totalSeats":2,"seats":{"CON":1,"STY":1}},"47":{"stateAbbr":"TN","pluralityParty":"CON","totalSeats":18,"seats":{"CON":4,"STY":4,"LIB":1,"CTR":4,"REF":2,"NAT":2,"SD":1}},"48":{"stateAbbr":"TX","pluralityParty":"STY","totalSeats":77,"seats":{"STY":14,"SD":14,"REF":12,"CON":14,"CTR":14,"LIB":4,"NAT":3,"DSA":2}},"49":{"stateAbbr":"UT","pluralityParty":"STY","totalSeats":9,"seats":{"REF":2,"STY":3,"CON":3,"SD":1}},"50":{"stateAbbr":"VT","pluralityParty":"SD","totalSeats":2,"seats":{"SD":1,"CON":1}},"51":{"stateAbbr":"VA","pluralityParty":"SD","totalSeats":23,"seats":{"SD":5,"STY":5,"DSA":1,"CON":5,"LIB":4,"CTR":2,"REF":1}},"53":{"stateAbbr":"WA","pluralityParty":"CON","totalSeats":20,"seats":{"CON":4,"LIB":4,"DSA":1,"SD":4,"STY":3,"REF":3,"CTR":1}},"54":{"stateAbbr":"WV","pluralityParty":"CON","totalSeats":5,"seats":{"CON":1,"STY":1,"CTR":1,"SD":1,"REF":1}},"55":{"stateAbbr":"WI","pluralityParty":"CON","totalSeats":16,"seats":{"CON":4,"LIB":2,"STY":3,"REF":3,"SD":4}},"56":{"stateAbbr":"WY","pluralityParty":"REF","totalSeats":2,"seats":{"REF":1,"CON":1}}}